friendly_module_not_found_error/__init__.py
friendly_module_not_found_error/__main__.py
friendly_module_not_found_error/handle_path.py
friendly_module_not_found_error/idlelib_all_change.py
friendly_module_not_found_error/importlib_change.py
friendly_module_not_found_error/runpy_change.py
friendly_module_not_found_error/traceback_change.py
friendly_module_not_found_error/wrong_child_module/__init__.py
friendly_module_not_found_error/wrong_child_module/wrong_child_module/__init__.py
friendly_module_not_found_error/wrong_child_module/wrong_child_module/wrong_child_modules.py
friendly_module_not_found_error/wrong_module/__init__.py
hatch_autorun_friendly_module_not_found_error.pth
friendly_module_not_found_error-1.0.28.dist-info/METADATA
friendly_module_not_found_error-1.0.28.dist-info/WHEEL
friendly_module_not_found_error-1.0.28.dist-info/entry_points.txt
friendly_module_not_found_error-1.0.28.dist-info/licenses/LICENSE
friendly_module_not_found_error-1.0.28.dist-info/RECORD
