Metadata-Version: 2.4
Name: friendly_module_not_found_error
Version: 1.0.28
Summary: Change the message in ModuleNotFoundError
Project-URL: Homepage, https://github.com/Locked-chess-official/friendly_module_not_found_error
Project-URL: Bug Reports, https://github.com/Locked-chess-official/friendly_module_not_found_error/issues
Project-URL: Source, https://github.com/Locked-chess-official/friendly_module_not_found_error
Author-email: Locked-chess-official <13140752715@163.com>
License: MIT
License-File: LICENSE
Requires-Python: >=3.7
